rag/__init__.py
rag/cli.py
rag/config.py
rag/ingest.py
rag/migrate.py
rag/ollama_check.py
rag/py.typed
rag/query.py
rag/store.py
rag/version.py
vector_bot-0.1.0.dist-info/licenses/LICENSE
vector_bot-0.1.0.dist-info/METADATA
vector_bot-0.1.0.dist-info/WHEEL
vector_bot-0.1.0.dist-info/entry_points.txt
vector_bot-0.1.0.dist-info/top_level.txt
vector_bot-0.1.0.dist-info/RECORD
