Metadata-Version: 2.4
Name: vector-bot
Version: 0.1.0
Summary: Vector Bot: A fully local RAG pipeline using LlamaIndex with Ollama
Author: Joshua Ramirez
License-Expression: MIT
Project-URL: Homepage, https://github.com/JoshuaRamirez/VectorBot
Project-URL: Repository, https://github.com/JoshuaRamirez/VectorBot
Project-URL: Issues, https://github.com/JoshuaRamirez/VectorBot/issues
Project-URL: Changelog, https://github.com/JoshuaRamirez/VectorBot/blob/master/CHANGELOG.md
Keywords: vector-bot,rag,ollama,llama-index,local,offline,embeddings,llm
Classifier: Development Status :: 4 - Beta
Classifier: Intended Audience :: Developers
Classifier: Intended Audience :: Science/Research
Classifier: Operating System :: OS Independent
Classifier: Programming Language :: Python :: 3
Classifier: Programming Language :: Python :: 3.10
Classifier: Programming Language :: Python :: 3.11
Classifier: Programming Language :: Python :: 3.12
Classifier: Topic :: Scientific/Engineering :: Artificial Intelligence
Classifier: Topic :: Software Development :: Libraries :: Python Modules
Requires-Python: >=3.10
License-File: LICENSE
Requires-Dist: llama-index-core>=0.10.0
Requires-Dist: llama-index-llms-ollama>=0.1.0
Requires-Dist: llama-index-embeddings-ollama>=0.1.0
Requires-Dist: python-dotenv>=1.0.0
Requires-Dist: requests>=2.31.0
Requires-Dist: rich>=13.7.0
Provides-Extra: dev
Requires-Dist: pytest>=7.4.0; extra == "dev"
Requires-Dist: mypy>=1.8.0; extra == "dev"
Requires-Dist: ruff>=0.1.0; extra == "dev"
Requires-Dist: types-requests>=2.31.0; extra == "dev"
Dynamic: license-file
